easy_sklearn/__init__.py
easy_sklearn/easy_base.py
easy_sklearn/easy_c.py
easy_sklearn/easy_r.py
easy_sklearn/utils.py
easy_sklearn-0.1.4.dist-info/METADATA
easy_sklearn-0.1.4.dist-info/RECORD
easy_sklearn-0.1.4.dist-info/WHEEL
easy_sklearn-0.1.4.dist-info/top_level.txt
