Metadata-Version: 2.1
Name: easy-sklearn
Version: 0.1.4
Summary: This is a python library base on sklearn
Home-page: https://github.com/ruifeng96150/easy_sklearn.git
Author: ruifeng96150
Author-email: ruifeng96150@163.com
License: MIT Licence
Keywords: sklearn,python,machine learning
Platform: any
Classifier: Development Status :: 4 - Beta
Classifier: Programming Language :: Python :: 2
Classifier: Programming Language :: Python :: 2.6
Classifier: Programming Language :: Python :: 2.7
Classifier: Programming Language :: Python :: 3
Classifier: Programming Language :: Python :: 3.3
Classifier: Programming Language :: Python :: 3.4
Classifier: Programming Language :: Python
Classifier: License :: OSI Approved :: MIT License
Classifier: Intended Audience :: Science/Research
Classifier: Intended Audience :: Developers
Requires-Dist: numpy
Requires-Dist: pandas
Requires-Dist: scikit-learn
